qcobj/__init__.py
qcobj/__version__.py
qcobj/cfggui.py
qcobj/qconfigobj.py
qcobj/utils.py
qcobj-1.2.7.dist-info/METADATA
qcobj-1.2.7.dist-info/WHEEL
qcobj-1.2.7.dist-info/top_level.txt
qcobj-1.2.7.dist-info/RECORD
