Metadata-Version: 2.1
Name: qcobj
Version: 1.2.7
Summary: A quantity aware configObject
Home-page: https://bitbucket.org/bvidmar/qcobj
Author: Roberto Vidmar
Author-email: rvidmar@inogs.it
License: MIT
Platform: UNKNOWN
Classifier: Programming Language :: Python :: 3.4
Classifier: Programming Language :: Python :: 3.6
Classifier: Programming Language :: Python :: 3.8
Classifier: License :: OSI Approved :: MIT License
Classifier: Operating System :: OS Independent
Requires-Dist: Pint (>=0.8.1)
Requires-Dist: configobj (>=5.0.6)
Requires-Dist: setuptools (>=39.0.1)
Provides-Extra: with_pyqt5
Requires-Dist: PyQt5 (>=5.14.1) ; extra == 'with_pyqt5'
Provides-Extra: with_pyside2
Requires-Dist: PySide2 (>=5.14.1) ; extra == 'with_pyside2'
